dcs_core/__init__.py
dcs_core/__main__.py
dcs_core/__version__.py
dcs_core/cli/__init__.py
dcs_core/cli/cli.py
dcs_core/core/__init__.py
dcs_core/core/common/__init__.py
dcs_core/core/common/errors.py
dcs_core/core/common/models/__init__.py
dcs_core/core/common/models/configuration.py
dcs_core/core/common/models/dashboard.py
dcs_core/core/common/models/data_source_resource.py
dcs_core/core/common/models/metric.py
dcs_core/core/common/models/profile.py
dcs_core/core/common/models/validation.py
dcs_core/core/common/models/widget.py
dcs_core/core/configuration/__init__.py
dcs_core/core/configuration/config_loader.py
dcs_core/core/configuration/configuration_parser.py
dcs_core/core/configuration/configuration_parser_arc.py
dcs_core/core/datasource/__init__.py
dcs_core/core/datasource/base.py
dcs_core/core/datasource/manager.py
dcs_core/core/datasource/search_datasource.py
dcs_core/core/datasource/sql_datasource.py
dcs_core/core/inspect.py
dcs_core/core/logger/__init__.py
dcs_core/core/logger/base.py
dcs_core/core/logger/default_logger.py
dcs_core/core/metric/__init__.py
dcs_core/core/metric/base.py
dcs_core/core/metric/combined_metric.py
dcs_core/core/metric/custom_metric.py
dcs_core/core/metric/manager.py
dcs_core/core/metric/numeric_metric.py
dcs_core/core/metric/reliability_metric.py
dcs_core/core/profiling/__init__.py
dcs_core/core/profiling/datasource_profiling.py
dcs_core/core/profiling/numeric_field_profiling.py
dcs_core/core/profiling/text_field_profiling.py
dcs_core/core/repository/__init__.py
dcs_core/core/repository/metric_repository.py
dcs_core/core/utils/__init__.py
dcs_core/core/utils/log.py
dcs_core/core/utils/tracking.py
dcs_core/core/utils/utils.py
dcs_core/core/validation/__init__.py
dcs_core/core/validation/base.py
dcs_core/core/validation/completeness_validation.py
dcs_core/core/validation/custom_query_validation.py
dcs_core/core/validation/manager.py
dcs_core/core/validation/numeric_validation.py
dcs_core/core/validation/reliability_validation.py
dcs_core-0.9.7.dist-info/METADATA
dcs_core-0.9.7.dist-info/WHEEL
dcs_core-0.9.7.dist-info/entry_points.txt
dcs_core-0.9.7.dist-info/licenses/LICENSE
dcs_core-0.9.7.dist-info/RECORD
