Metadata-Version: 2.4
Name: dcs-core
Version: 0.9.7
Summary: Open Source Data Quality Monitoring
License: Apache-2.0
License-File: LICENSE
Author: Waterdip Labs
Author-email: hello@waterdip.ai
Requires-Python: >=3.10,<3.13
Classifier: Development Status :: 3 - Alpha
Classifier: Environment :: Console
Classifier: Intended Audience :: Developers
Classifier: Intended Audience :: Information Technology
Classifier: Intended Audience :: System Administrators
Classifier: License :: OSI Approved :: Apache Software License
Classifier: Programming Language :: Python :: 3
Classifier: Programming Language :: Python :: 3.10
Classifier: Programming Language :: Python :: 3.11
Classifier: Programming Language :: Python :: 3.12
Classifier: Programming Language :: Python :: 3.9
Classifier: Topic :: Database :: Database Engines/Servers
Classifier: Typing :: Typed
Provides-Extra: all
Provides-Extra: bigquery
Provides-Extra: databricks
Provides-Extra: db2
Provides-Extra: elasticsearch
Provides-Extra: ms-sql
Provides-Extra: mysql
Provides-Extra: opensearch
Provides-Extra: oracle
Provides-Extra: postgres
Provides-Extra: snowflake
Provides-Extra: spark
Provides-Extra: sybase
Requires-Dist: click (>=8.1.5,<9.0.0)
Requires-Dist: databricks-sql-connector (>=3.3.0,<4.0.0) ; extra == "databricks" or extra == "all"
Requires-Dist: elasticsearch (>=9.1.0,<10.0.0) ; extra == "elasticsearch" or extra == "all"
Requires-Dist: h11 (>=0.16.0,<0.17.0)
Requires-Dist: ibm-db (>=3.2.3,<4.0.0) ; extra == "db2" or extra == "all"
Requires-Dist: ibm-db-sa (>=0.4.1,<0.5.0) ; extra == "db2" or extra == "all"
Requires-Dist: jinja2 (>=3.1.6,<4.0.0)
Requires-Dist: loguru (>=0.7.0,<0.8.0)
Requires-Dist: numpy (==1.26.4)
Requires-Dist: opensearch-py (>=2.2.0,<3.0.0) ; extra == "opensearch" or extra == "all"
Requires-Dist: oracledb (>=1.1.1,<3.0.0) ; extra == "oracle" or extra == "all"
Requires-Dist: protobuf (>=5.29.5,<6.0.0)
Requires-Dist: psycopg2-binary (>=2.9.9,<3.0.0) ; extra == "postgres" or extra == "all"
Requires-Dist: pymysql[rsa] (>=1.1.0,<2.0.0) ; extra == "mysql" or extra == "all"
Requires-Dist: pyodbc (>=5.0.1,<6.0.0) ; extra == "ms-sql" or extra == "all"
Requires-Dist: pyparsing (>=3.1.1,<4.0.0)
Requires-Dist: pyspark (>=3.2.1,<4.0.0) ; extra == "spark" or extra == "all"
Requires-Dist: python-dateutil (>=2.8.2,<3.0.0)
Requires-Dist: pytz (>=2024.1)
Requires-Dist: pyyaml (>=6.0,<7.0)
Requires-Dist: requests (>=2.32.4,<3.0.0)
Requires-Dist: rich (>=13.5.2,<14.0.0)
Requires-Dist: setuptools (>=78.1.1)
Requires-Dist: snowflake-connector-python (>=3.17.2,<4.0.0) ; extra == "snowflake"
Requires-Dist: snowflake-sqlalchemy (>=1.5.3,<2.0.0) ; extra == "snowflake" or extra == "all"
Requires-Dist: sqlalchemy (>=2.0.14,<2.1.0)
Requires-Dist: sqlalchemy-bigquery (>=1.8.0,<2.0.0) ; extra == "bigquery" or extra == "all"
Requires-Dist: sqlalchemy-sybase (>=2.0.0,<3.0.0) ; extra == "sybase" or extra == "all"
Requires-Dist: tornado (>=6.5,<7.0)
Requires-Dist: urllib3 (>=2.5.0,<3.0.0)
Project-URL: Repository, https://github.com/datachecks/dcs-core
